leapfrog_py/__init__.py
leapfrog_py/_core.cpython-313-x86_64-linux-gnu.so
leapfrog_py/_core.pyi
leapfrog_py/py.typed
leapfrog_py-1.0.0.dist-info/METADATA
leapfrog_py-1.0.0.dist-info/WHEEL
leapfrog_py-1.0.0.dist-info/RECORD
leapfrog_py-1.0.0.dist-info/licenses/LICENSE.txt
