Metadata-Version: 2.1
Name: leapfrog-py
Version: 1.0.0
Summary: Python interface for Leapfrog model
Author-Email: Mantra <mantrakusumgar@outlook.com>, Rob Ashton <robertashton94@gmail.com>
Project-URL: Documentation, https://github.com/mrc-ide/leapfrog#readme
Project-URL: Issues, https://github.com/mrc-ide/leapfrog/issues
Project-URL: Source, https://github.com/mrc-ide/leapfrog
Requires-Python: >=3.8
Requires-Dist: h5py>=3.11.0
Requires-Dist: numpy>=1.24.4
